README.rst
setup.py
tvsort/__init__.py
tvsort/tvsort.py
tvsort.egg-info/PKG-INFO
tvsort.egg-info/SOURCES.txt
tvsort.egg-info/dependency_links.txt
tvsort.egg-info/entry_points.txt
tvsort.egg-info/requires.txt
tvsort.egg-info/top_level.txt