Metadata-Version: 1.0
Name: tvsort
Version: 0.2
Summary: Sort TV episodes
Home-page: https://github.com/spillevink/tvsort
Author: Jakob Hedman
Author-email: jakob@hedman.email
License: GNU GPLv3
Platform: UNKNOWN
